Metadata-Version: 2.1
Name: ChopChop-np-conflict
Version: 0.1.0
Summary: Data Analysis conflicting dependencies taks
Home-page: UNKNOWN
Author: Karen Armenakyan
Author-email: 284567@niuitmo.ru
License: UNKNOWN
Platform: UNKNOWN
